PySiddhi/SiddhiLoader.py
PySiddhi/__init__.py
PySiddhi/DataTypes/DataWrapper.py
PySiddhi/DataTypes/DoubleType.py
PySiddhi/DataTypes/LongType.py
PySiddhi/DataTypes/__init__.py
PySiddhi/core/SiddhiAppRuntime.py
PySiddhi/core/SiddhiManager.py
PySiddhi/core/__init__.py
PySiddhi/core/debugger/SiddhiDebugger.py
PySiddhi/core/debugger/SiddhiDebuggerCallback.py
PySiddhi/core/debugger/__init__.py
PySiddhi/core/event/ComplexEvent.py
PySiddhi/core/event/Event.py
PySiddhi/core/event/__init__.py
PySiddhi/core/query/__init__.py
PySiddhi/core/query/output/__init__.py
PySiddhi/core/query/output/callback/QueryCallback.py
PySiddhi/core/query/output/callback/__init__.py
PySiddhi/core/stream/__init__.py
PySiddhi/core/stream/input/InputHandler.py
PySiddhi/core/stream/input/__init__.py
PySiddhi/core/stream/output/StreamCallback.py
PySiddhi/core/stream/output/__init__.py
PySiddhi/core/util/EventPrinter.py
PySiddhi/core/util/__init__.py
PySiddhi/sp/SPClient.py
PySiddhi/sp/__Util.py
PySiddhi/sp/__init__.py
PySiddhi/sp/EventSimulator/AttributeConfiguration.py
PySiddhi/sp/EventSimulator/EventSimulatorClient.py
PySiddhi/sp/EventSimulator/FeedSimulationConfiguration.py
PySiddhi/sp/EventSimulator/SimulationProperties.py
PySiddhi/sp/EventSimulator/SimulationSource.py
PySiddhi/sp/EventSimulator/SingleSimulationConfiguration.py
PySiddhi/sp/EventSimulator/__init__.py
PySiddhi/sp/ObjectMapping/APIObject.py
PySiddhi/sp/ObjectMapping/FieldMapping.py
PySiddhi/sp/ObjectMapping/__init__.py
PySiddhi/sp/SiddhiAppManagement/SiddhiAppManagementClient.py
PySiddhi/sp/SiddhiAppManagement/__init__.py
PySiddhi/sp/__Communication/RestClient.py
PySiddhi/sp/__Communication/__init__.py
__PySiddhiProxy/libio_siddhi_pythonapi_threadfix_pythreadfix.so
__PySiddhiProxy/target/siddhi-python-api-proxy-5.1.0.jar
__PySiddhiProxy/target/lib/accessors-smart-1.2.jar
__PySiddhiProxy/target/lib/animal-sniffer-annotations-1.14.jar
__PySiddhiProxy/target/lib/antlr4-runtime-4.7.2.jar
__PySiddhiProxy/target/lib/asm-5.0.4.jar
PySiddhi_localstack-5.1.0.post2.dist-info/LICENSE.txt
PySiddhi_localstack-5.1.0.post2.dist-info/METADATA
PySiddhi_localstack-5.1.0.post2.dist-info/WHEEL
PySiddhi_localstack-5.1.0.post2.dist-info/top_level.txt
PySiddhi_localstack-5.1.0.post2.dist-info/RECORD
